{   
    "title" : "Architecture",
    "description" : "Flux is a five (5) node cluster with one head node, one large memory node, and three compute nodes.  The three compute nodes are managed by a SLURM scheduler.  Each compute node contains x processor cores, y sockets, and z RAM as can be seen in the hwloc diagrams.",
    "specifications" : {
        "Total Nodes" : 5,
        "Total Cores" : 48,
        "Total RAM" : "624 GB"
    },
    
    "subtitle" : "hwloc Node Diagrams",
    "nodes" : 
    [
        {   
            "name" : "Flux (head node)",
            "specs" : [ 
                    "Cores per node : 12",
                    "RAM per node : 96 GB"
           ],
            "img" : "img/flux.png"
        },
        {
            "name" : "Flux 1 (large memory)",
            "specs" : [ 
                    "Cores per node : 12",
                    "RAM per node : 384 GB"
           ],
            "img" : "img/flux1.png"
        },
        {
            "name" : "Flux 2 (compute node)",
            "specs" : [ 
                    "Cores per node : 8",
                    "RAM per node : 48 GB"
            ],
            "img" : "img/flux2.png"
        },
        {
            "name" : "Flux 3 (compute node)",
            "specs" : [ 
                    "Cores per node : 8",
                    "RAM per node : 48 GB"
            ],
            "img" : "img/flux3.png"
            
        },
        {
            "name" : "Flux 4 (compute node) ",
            "specs" : [ 
                    "Cores per node : 8",
                    "RAM per node : 48 GB"
            ],
            "img" : "img/flux4.png"
        }
    ],
    
    "buttons" : {
        "previous" : "Previous Diagram",
        "next" : "Next Diagram",
        "back": "Back To Gallery"
    }
}